omc_arthas/__init__.py
omc_arthas/arthas/__init__.py
omc_arthas/arthas/arthas.py
omc_arthas/lib/__init__.py
omc_arthas/lib/arthas-boot.jar
omc_arthas/lib/__pycache__/__init__.cpython-37.pyc
omc_arthas-0.0.2.dist-info/METADATA
omc_arthas-0.0.2.dist-info/WHEEL
omc_arthas-0.0.2.dist-info/top_level.txt
omc_arthas-0.0.2.dist-info/RECORD
