Metadata-Version: 2.1
Name: omc-arthas
Version: 0.0.2
Summary: arthas plugin for omc
Home-page: https://github.com/linewx/omc-arthas
Author: Lu Ganlin
Author-email: linewx1981@gmail.com
License: MIT
Platform: UNKNOWN
Requires-Dist: omc (>=0.2.1)
